Metadata-Version: 2.1
Name: sperocoin-x13-hash
Version: 1.0.6
Summary: Bindings for proof of work used by x13
Home-page: https://github.com/DigitalCoin1/sperocoin-x13-hash
License: UNKNOWN
Platform: UNKNOWN
